[
	{
		"title": "Europe Street beat",
		"url": "https://os.alipayobjects.com/rmsportal/QBnOOoLaAfKPirc.png",
		"description": "www.instagram.com"
	},
	{
		"title": "Europe Street beat222",
		"url": "https://os.alipayobjects.com/rmsportal/QBnOOoLaAfKPirc.png",
		"description": "www.instagram.comgggg"
	},
	{
		"title": "Europe Street beat33333",
		"url": "https://os.alipayobjects.com/rmsportal/QBnOOoLaAfKPirc.png",
		"description": "www.instagram.comxxxx"
	},
	{
		"title": "Europe Street beat222",
		"url": "https://os.alipayobjects.com/rmsportal/QBnOOoLaAfKPirc.png",
		"description": "www.instagram.comgggg"
	},
	{
		"title": "Europe Street beat33333",
		"url": "https://os.alipayobjects.com/rmsportal/QBnOOoLaAfKPirc.png",
		"description": "www.instagram.comxxxx"
	},
	{
		"title": "Europe Street beat222",
		"url": "https://os.alipayobjects.com/rmsportal/QBnOOoLaAfKPirc.png",
		"description": "www.instagram.comgggg"
	},
	{
		"title": "Europe Street beat33333",
		"url": "https://os.alipayobjects.com/rmsportal/QBnOOoLaAfKPirc.png",
		"description": "www.instagram.comxxxx"
	}
]